{  
  "Beschreibung":"Der DAX ist der bedeutendste deutsche Aktienindex. Er misst aktuell die Wertentwicklung der 40 größten und liquidesten Unternehmen des deutschen Aktienmarktes und repräsentiert rund 80 Prozent der Marktkapitalisierung börsennotierter Aktiengesellschaften in Deutschland",
  "DAX_Values": [
    {
      "year": 2014,
      "value": 9800.03
    },
    {
      "year": 2015,
      "value": 10743.01
    },
    {
      "year": 2016,
      "value": 11481.06
    },
    {
      "year": 2017,
      "value": 12917.64
    },
    {
      "year": 2018,
      "value": 10858.68
    },
    {
      "year": 2019,
      "value": 13249.01
    },
    {
      "year": 2020,
      "value": 13718.78
    },
    {
      "year": 2021,
      "value": 15835.09
    },
    {
      "year": 2022,
      "value": 13923.59
    }
  ]  
}
